{
  "mealId": "shrimp-simmered-in-green-mole-from-nom-nom-paleo-let-s-go-si-e2d37c10",
  "fetchedAt": "2026-06-17T15:05:08.343Z",
  "source": "paprika",
  "url": "https://www.eatyourbooks.com/library/recipes/2678328/shrimp-simmered-in-green-mole",
  "name": "Shrimp Simmered in Green Mole From Nom Nom Paleo Let's Go!: Simple Feasts + Healthy Eats (Page 160) by And",
  "description": "",
  "recipeIngredient": [
    "jalapeño chiles",
    "tomatillos",
    "Show all ingredients..."
  ],
  "recipeInstructions": [],
  "prepTime": null,
  "cookTime": null,
  "totalTime": null,
  "recipeYield": null,
  "image": null,
  "author": "eatyourbooks.com",
  "categories": [
    "Paleo"
  ],
  "rating": null,
  "notes": null,
  "nutrition": null,
  "ai": null
}
