{
  "mealId": "sicilian-fish-stew-e047a9f8",
  "fetchedAt": "2026-06-18T04:20:31.183Z",
  "source": "cookbook",
  "url": null,
  "name": "Sicilian Fish Stew",
  "description": "From The Complete Mediterranean Cookbook (ATK) — p.267. NEEDS SCAN — title placeholder; capture ingredients/method from the book page before cooking.",
  "recipeIngredient": [],
  "recipeInstructions": [],
  "prepTime": null,
  "cookTime": null,
  "totalTime": null,
  "recipeYield": "4 servings",
  "image": null,
  "author": null,
  "ai": null
}
