{
  "household": {
    "people": 2,
    "adults": 2,
    "kids": 0,
    "defaultServings": 4,
    "notes": ""
  },
  "schedule": {
    "daysToPlan": [
      "Sun",
      "Mon",
      "Tue",
      "Wed",
      "Thu",
      "Fri",
      "Sat"
    ],
    "mealsPerDay": [
      "dinner"
    ],
    "weekendDays": [
      "Sat",
      "Sun"
    ]
  },
  "preferences": {
    "cuisines": {
      "love": [
        "italian",
        "thai",
        "mexican",
        "mediterranean",
        "japanese",
        "french",
        "chinese",
        "korean"
      ],
      "ok": [
        "american",
        "indian",
        "spanish",
        "vietnamese"
      ],
      "avoid": []
    },
    "preferredSites": [
      "seriouseats.com",
      "smittenkitchen.com",
      "thekitchn.com",
      "epicurious.com",
      "thewoksoflife.com",
      "justonecookbook.com",
      "maangchi.com",
      "themediterraneandish.com",
      "isabeleats.com",
      "the-pasta-project.com",
      "pardonyourfrench.com",
      "heygrillhey.com"
    ],
    "avoidSites": []
  },
  "proteinRules": {
    "redMeatMaxPerWeek": 1,
    "poultryMaxPerWeek": 3,
    "seafoodMinPerWeek": 1,
    "vegetarianMinPerWeek": 0,
    "vegetarianMaxPerWeek": 1,
    "noRepeatProteinTwoDaysInRow": true,
    "classification": {
      "red_meat": [
        "beef",
        "pork",
        "lamb",
        "veal",
        "goat",
        "venison",
        "bison",
        "sausage"
      ],
      "poultry": [
        "chicken",
        "turkey",
        "duck"
      ],
      "seafood": [
        "fish",
        "salmon",
        "tuna",
        "cod",
        "shrimp",
        "scallop",
        "crab",
        "lobster",
        "clam",
        "mussel",
        "trout",
        "halibut",
        "mahi",
        "snapper",
        "bass",
        "tilapia",
        "swordfish",
        "seafood"
      ],
      "vegetarian": [
        "tofu",
        "tempeh",
        "bean",
        "lentil",
        "chickpea",
        "egg",
        "paneer",
        "vegetable",
        "veg",
        "vegetarian",
        "vegan",
        "mushroom"
      ]
    }
  },
  "carbRules": {
    "riceMaxPerWeek": 3,
    "riceHardMaxPerWeek": 4,
    "fourthRiceMustNotBeAllWhite": true,
    "noRiceThreeDaysInRow": true,
    "risottoExempt": true
  },
  "ingredients": {
    "dislikes": [
      "liver",
      "organ meat",
      "curry",
      "broccoli"
    ],
    "allergies": [],
    "favorites": [
      "chicken",
      "shrimp",
      "fish",
      "bacon"
    ],
    "pantryStaples": [
      "salt",
      "black pepper",
      "olive oil",
      "vegetable oil",
      "water",
      "butter",
      "all-purpose flour",
      "sugar",
      "baking soda",
      "baking powder",
      "soy sauce"
    ]
  },
  "constraints": {
    "maxActiveMinutesWeeknight": 45,
    "maxActiveMinutesWeekend": 120,
    "weeknightDifficulty": "easy-to-medium",
    "leftoversOk": true,
    "avoidRepeatWithinDays": 21,
    "useSeasonalProduce": true
  },
  "nutrition": {
    "goals": [
      "heart-healthy",
      "good",
      "chefy"
    ],
    "notes": "need to keep bean usage low. Household has high total cholesterol + high LDL (as of 2026-06) \u2014 lean heart-healthy: cap saturated fat (butter/cream/cheese, fatty red meat, bacon/sausage, fried foods), favor olive oil + unsaturated fats, omega-3 fish ~2x/week, and get fiber from oats/whole grains/veg/fruit (NOT beans). Soft lean layered on the existing rules; guest/celebration nights can still flex.",
    "dairy": "low",
    "saturatedFat": "low",
    "cholesterolConscious": true
  },
  "shopping": {
    "excludePantryStaples": true,
    "aisleOrder": [
      "produce",
      "meat-seafood",
      "dairy",
      "bakery",
      "deli",
      "pantry",
      "canned",
      "spices",
      "frozen",
      "beverages",
      "other"
    ]
  }
}